tools_collections_python/__init__.py
tools_collections_python/rsshub/__init__.py
tools_collections_python/rsshub/game/__init__.py
tools_collections_python/rsshub/game/epic_free.py
tools_collections_python/rsshub/game/history_low.py
tools_collections_python/rsshub/game/steam_search.py
tools_collections_python/rsshub/github/__init__.py
tools_collections_python/rsshub/github/search.py
tools_collections_python/rsshub/github/trending.py
tools_collections_python/rsshub/news/__init__.py
tools_collections_python/rsshub/news/bahamute_news.py
tools_collections_python/rsshub/news/baidu_top.py
tools_collections_python/rsshub/pixiv/__init__.py
tools_collections_python/rsshub/pixiv/auth.py
tools_collections_python/rsshub/pixiv/ranking.py
tools_collections_python/rsshub/pixiv/search.py
tools_collections_python/rsshub/video/__init__.py
tools_collections_python/rsshub/video/douban_month_recommend.py
tools_collections_python/rsshub/wechat/__init__.py
tools_collections_python/rsshub/wechat/announce.py
tools_collections_python-0.0.9.dist-info/METADATA
tools_collections_python-0.0.9.dist-info/WHEEL
tools_collections_python-0.0.9.dist-info/top_level.txt
tools_collections_python-0.0.9.dist-info/RECORD
