Metadata-Version: 2.1
Name: tools-collections-python
Version: 0.0.9
Summary: tools for some open-source projects
Home-page: https://gitee.com/itdqj/tools_collections_python
Author: pikad
Author-email: 1195628604@qq.com
License: MIT
Classifier: Development Status :: 3 - Alpha
Classifier: Intended Audience :: Developers
Classifier: License :: OSI Approved :: MIT License
Classifier: Programming Language :: Python :: 3.11
Requires-Python: >=3.11
